dicteval/__init__.py
dicteval/exceptions.py
dicteval-0.0.6.dist-info/LICENSE
dicteval-0.0.6.dist-info/METADATA
dicteval-0.0.6.dist-info/WHEEL
dicteval-0.0.6.dist-info/top_level.txt
dicteval-0.0.6.dist-info/RECORD
