Metadata-Version: 2.1
Name: dicteval
Version: 0.0.6
Summary: Evaluate expressions in dict/json objects
Home-page: https://github.com/osantana/dicteval
Author: Osvaldo Santana Neto
Author-email: dicteval@osantana.me
License: MIT
Platform: UNKNOWN
Classifier: License :: OSI Approved :: MIT License
Classifier: Programming Language :: Python
Classifier: Programming Language :: Python :: 3
Classifier: Programming Language :: Python :: 3.7
Classifier: Programming Language :: Python :: Implementation :: CPython
Classifier: Programming Language :: Python :: Implementation :: PyPy
Requires-Python: >=3.7.0
